dlen/__init__.py
dlen/__version__.py
dlen/dlen.py
dlen-0.0.2.dist-info/DESCRIPTION.rst
dlen-0.0.2.dist-info/METADATA
dlen-0.0.2.dist-info/RECORD
dlen-0.0.2.dist-info/WHEEL
dlen-0.0.2.dist-info/entry_points.txt
dlen-0.0.2.dist-info/metadata.json
dlen-0.0.2.dist-info/top_level.txt
